{
	"monsterName": "Dwarf Guard",
	"timesKilled": 33522,
	"items": [
		{
			"itemName": "White Mushroom",
			"timesDropped": 18512
		},
		{
			"itemName": "Leather Boots",
			"timesDropped": 13430
		},
		{
			"itemName": "Gold Coin",
			"timesDropped": 13396
		},
		{
			"itemName": "Scale Armor",
			"timesDropped": 3017
		},
		{
			"itemName": "Battle Shield",
			"timesDropped": 2015
		},
		{
			"itemName": "Battle Hammer",
			"timesDropped": 1291
		},
		{
			"itemName": "Steel Helmet",
			"timesDropped": 521
		},
		{
			"itemName": "Double Axe",
			"timesDropped": 198
		},
		{
			"itemName": "Iron Ore",
			"timesDropped": 162
		},
		{
			"itemName": "Health Potion",
			"timesDropped": 131
		},
		{
			"itemName": "Axe Ring",
			"timesDropped": 66
		},
		{
			"itemName": "Coal",
			"timesDropped": 65
		},
		{
			"itemName": "Small Amethyst",
			"timesDropped": 40
		}
	]
}
