{
	"monsterName": "Lizard Dragon Priest",
	"timesKilled": 53720,
	"items": [
		{
			"itemName": "Gold Coin",
			"timesDropped": 50443
		},
		{
			"itemName": "Strong Mana Potion",
			"timesDropped": 6503
		},
		{
			"itemName": "Dragon Priest's Wandtip",
			"timesDropped": 5354
		},
		{
			"itemName": "Great Mana Potion",
			"timesDropped": 4319
		},
		{
			"itemName": "Small Amethyst",
			"timesDropped": 2620
		},
		{
			"itemName": "Platinum Coin",
			"timesDropped": 2160
		},
		{
			"itemName": "Wand of Inferno",
			"timesDropped": 831
		},
		{
			"itemName": "Lizard Scale",
			"timesDropped": 574
		},
		{
			"itemName": "Lizard Leather",
			"timesDropped": 566
		},
		{
			"itemName": "Terra Rod",
			"timesDropped": 537
		},
		{
			"itemName": "Yellow Gem",
			"timesDropped": 522
		},
		{
			"itemName": "Bunch of Ripe Rice",
			"timesDropped": 518
		},
		{
			"itemName": "Life Ring",
			"timesDropped": 419
		},
		{
			"itemName": "Focus Cape",
			"timesDropped": 357
		},
		{
			"itemName": "Zaoan Shoes",
			"timesDropped": 233
		},
		{
			"itemName": "Zaoan Robe",
			"timesDropped": 155
		}
	]
}
