{
	"monsterName": "Monk",
	"timesKilled": 30569,
	"items": [
		{
			"itemName": "Bread",
			"timesDropped": 6087
		},
		{
			"itemName": "Gold Coin",
			"timesDropped": 4590
		},
		{
			"itemName": "Book of Prayers",
			"timesDropped": 1546
		},
		{
			"itemName": "Rope Belt",
			"timesDropped": 908
		},
		{
			"itemName": "Ankh",
			"timesDropped": 661
		},
		{
			"itemName": "Scroll",
			"timesDropped": 576
		},
		{
			"itemName": "Safety Pin",
			"timesDropped": 318
		},
		{
			"itemName": "Life Crystal",
			"timesDropped": 308
		},
		{
			"itemName": "Brown Flask",
			"timesDropped": 269
		},
		{
			"itemName": "Lamp",
			"timesDropped": 265
		},
		{
			"itemName": "Sandals",
			"timesDropped": 232
		},
		{
			"itemName": "Staff",
			"timesDropped": 145
		},
		{
			"itemName": "Power Ring",
			"timesDropped": 32
		}
	]
}
